elefast/__init__.py
elefast/asyncio.py
elefast/cli/__init__.py
elefast/cli/docker.py
elefast/cli/init.py
elefast/cli/parser.py
elefast/cli/types.py
elefast/docker/__init__.py
elefast/docker/configuration.py
elefast/docker/integration.py
elefast/docker/optimization_docs.py
elefast/docker/orchestration.py
elefast/errors.py
elefast/sync.py
elefast-0.1.0a2.dist-info/WHEEL
elefast-0.1.0a2.dist-info/entry_points.txt
elefast-0.1.0a2.dist-info/METADATA
elefast-0.1.0a2.dist-info/RECORD
