Metadata-Version: 2.4
Name: elefast
Version: 0.1.0a2
Summary: Database testing toolkit integrating Postgres, SQLAlchemy, Pytest and Docker
License-Expression: MIT
Classifier: Development Status :: 3 - Alpha
Classifier: License :: OSI Approved :: MIT License
Classifier: Framework :: AsyncIO
Classifier: Framework :: Pytest
Classifier: Programming Language :: Python
Classifier: Programming Language :: Python :: 3.14
Classifier: Topic :: Education :: Testing
Classifier: Topic :: Software Development :: Testing
Classifier: Topic :: Software Development :: Documentation
Classifier: Topic :: Database
Requires-Dist: sqlalchemy>=2.0.45
Requires-Dist: docker>=7.1.0 ; extra == 'docker'
Requires-Dist: filelock>=3.20.3 ; extra == 'docker'
Requires-Python: >=3.14
Provides-Extra: docker
